setup2upypackage/__init__.py
setup2upypackage/main.py
setup2upypackage/setup2upypackage.py
setup2upypackage/version.py
setup2upypackage-0.5.0.dist-info/LICENSE.txt
setup2upypackage-0.5.0.dist-info/METADATA
setup2upypackage-0.5.0.dist-info/WHEEL
setup2upypackage-0.5.0.dist-info/entry_points.txt
setup2upypackage-0.5.0.dist-info/top_level.txt
setup2upypackage-0.5.0.dist-info/RECORD
