Metadata-Version: 2.1
Name: setup2upypackage
Version: 0.5.0
Summary: Validate and create MicroPython package JSON file
Home-page: https://github.com/brainelectronics/micropython-package-validation
Author: brainelectronics
Author-email: info@brainelectronics.de
Project-URL: Bug Reports, https://github.com/brainelectronics/micropython-package-validation/issues
Project-URL: Source, https://github.com/brainelectronics/micropython-package-validation/
Keywords: micropython,package,mip-helper,validation
Classifier: Development Status :: 5 - Production/Stable
Classifier: Intended Audience :: Developers
Classifier: Topic :: Software Development :: Build Tools
Classifier: License :: OSI Approved :: MIT License
Classifier: Programming Language :: Python :: 3
Classifier: Programming Language :: Python :: 3.7
Classifier: Programming Language :: Python :: 3.8
Classifier: Programming Language :: Python :: 3.9
Classifier: Programming Language :: Python :: 3.10
Classifier: Programming Language :: Python :: 3 :: Only
Requires-Python: >=3.7, <4
License-File: LICENSE.txt
Requires-Dist: changelog2version (<1,>=0.9.0)
Requires-Dist: deepdiff (<7,>=6.3.0)
Requires-Dist: mock (<5,>=4.0.3)
Provides-Extra: dev
Requires-Dist: tox (<4,>=3.25.1) ; extra == 'dev'
Provides-Extra: test
Requires-Dist: flake8 (<6,>=5.0.0) ; extra == 'test'
Requires-Dist: coverage (<7,>=6.4.2) ; extra == 'test'
Requires-Dist: nose2 (<1,>=0.12.0) ; extra == 'test'
Requires-Dist: yamllint (<2,>=1.29) ; extra == 'test'
